setup.py
lyricCheck/__init__.py
lyricCheck/lyricCheck.py
lyricCheck.egg-info/PKG-INFO
lyricCheck.egg-info/SOURCES.txt
lyricCheck.egg-info/dependency_links.txt
lyricCheck.egg-info/requires.txt
lyricCheck.egg-info/top_level.txt