Metadata-Version: 1.0
Name: lyricCheck
Version: 1.0
Summary: Uses pygoogle to check songs for explitives in the lyics.  Checks for the seven dirty words.
Home-page: jimboulter.com
Author: Jim Boulter
Author-email: jboulter11@gmail.com
License: UNKNOWN
Platform: UNKNOWN
